acgc/__init__.py
acgc/acgc.mplstyle
acgc/boxcar.py
acgc/bstats.py
acgc/erroranalysis.py
acgc/figstyle.py
acgc/gc.py
acgc/geoschem.py
acgc/hysplit.py
acgc/hytools.py
acgc/icartt.py
acgc/igra.py
acgc/mapping.py
acgc/met.py
acgc/mettools.py
acgc/modetools.py
acgc/nctools.py
acgc/netcdf.py
acgc/sen_slope.py
acgc/smafit.py
acgc/solar.py
acgc/time.py
acgc/timetools.py
acgc/wstats.py
acgc/fonts/texgyreadventor-bold.otf
acgc/fonts/texgyreadventor-bolditalic.otf
acgc/fonts/texgyreadventor-italic.otf
acgc/fonts/texgyreadventor-regular.otf
acgc/fonts/texgyrechorus-mediumitalic.otf
acgc/fonts/texgyrecursor-bold.otf
acgc/fonts/texgyrecursor-bolditalic.otf
acgc/fonts/texgyrecursor-italic.otf
acgc/fonts/texgyrecursor-regular.otf
acgc/fonts/texgyreheros-bold.otf
acgc/fonts/texgyreheros-bolditalic.otf
acgc/fonts/texgyreheros-italic.otf
acgc/fonts/texgyreheros-regular.otf
acgc/fonts/texgyreheroscn-bold.otf
acgc/fonts/texgyreheroscn-bolditalic.otf
acgc/fonts/texgyreheroscn-italic.otf
acgc/fonts/texgyreheroscn-regular.otf
acgc/fonts/texgyrepagella-bold.otf
acgc/fonts/texgyrepagella-bolditalic.otf
acgc/fonts/texgyrepagella-italic.otf
acgc/fonts/texgyrepagella-math.otf
acgc/fonts/texgyrepagella-regular.otf
acgc/fonts/texgyreschola-bold.otf
acgc/fonts/texgyreschola-bolditalic.otf
acgc/fonts/texgyreschola-italic.otf
acgc/fonts/texgyreschola-math.otf
acgc/fonts/texgyreschola-regular.otf
acgc/fonts/texgyretermes-bold.otf
acgc/fonts/texgyretermes-bolditalic.otf
acgc/fonts/texgyretermes-italic.otf
acgc/fonts/texgyretermes-math.otf
acgc/fonts/texgyretermes-regular.otf
acgc/stats/__init__.py
acgc/stats/bivariate.py
acgc/stats/bivariate_lines.py
acgc/stats/boxcar.py
acgc/stats/loess.py
acgc/stats/partial_corr.py
acgc/stats/sma_warton_fit.py
acgc/stats/tapply.py
acgc/stats/weighted.py
acgc-0.3.1.dist-info/LICENSE
acgc-0.3.1.dist-info/METADATA
acgc-0.3.1.dist-info/WHEEL
acgc-0.3.1.dist-info/top_level.txt
acgc-0.3.1.dist-info/RECORD
