Metadata-Version: 2.1
Name: acgc
Version: 0.3.1
Summary: A collection of data analysis programs used by the Atmospheric Chemistry and Global Change (ACGC) research group
Author-email: Christopher Holmes <cdholmes@fsu.edu>
Maintainer-email: Christopher Holmes <cdholmes@fsu.edu>
License: GNU LESSER GENERAL PUBLIC LICENSE
Project-URL: Homepage, https://github.com/cdholmes/acgc-python
Project-URL: Documentation, https://cdholmes.github.io/acgc-python
Project-URL: Repository, https://github.com/cdholmes/acgc-python
Classifier: Programming Language :: Python :: 3
Classifier: Operating System :: OS Independent
Classifier: License :: OSI Approved :: GNU Lesser General Public License v3 or later (LGPLv3+)
Classifier: Intended Audience :: Science/Research
Classifier: Topic :: Scientific/Engineering
Classifier: Topic :: Scientific/Engineering :: Atmospheric Science
Requires-Python: >=3.4
License-File: LICENSE
Requires-Dist: matplotlib
Requires-Dist: matplotlib-inline
Requires-Dist: cartopy
Requires-Dist: numpy
Requires-Dist: scipy
Requires-Dist: pandas
Requires-Dist: netCDF4
Requires-Dist: scikit-learn
Requires-Dist: statsmodels
Requires-Dist: cmcrameri
Provides-Extra: test
Requires-Dist: xarray ; extra == 'test'
